transientNamer/.DS_Store
transientNamer/__init__.py
transientNamer/__version__.py
transientNamer/astronotes.py
transientNamer/cl_utils.py
transientNamer/default_settings.yaml
transientNamer/search.py
transientNamer/test_settings.yaml
transientNamer/utKit.py
transientNamer/commonutils/__init__.py
transientNamer/commonutils/getpackagepath.py
transientNamer/resources/package.mplstyle
transientNamer-0.4.9.dist-info/LICENSE
transientNamer-0.4.9.dist-info/METADATA
transientNamer-0.4.9.dist-info/WHEEL
transientNamer-0.4.9.dist-info/entry_points.txt
transientNamer-0.4.9.dist-info/top_level.txt
transientNamer-0.4.9.dist-info/RECORD
