Metadata-Version: 2.1
Name: transientNamer
Version: 0.4.9
Summary: Python API for reading and caching TNS reports
Home-page: https://github.com/thespacedoctor/transientNamer
Download-URL: https://github.com/thespacedoctor/transientNamer/archive/v0.4.9.zip
Author: David Young
Author-email: davidrobertyoung@gmail.com
License: MIT
Keywords: astronomy, transients
Classifier: Development Status :: 4 - Beta
Classifier: License :: OSI Approved :: MIT License
Classifier: Programming Language :: Python :: 3.7
Classifier: Topic :: Utilities
License-File: LICENSE
Requires-Dist: pyyaml
Requires-Dist: transientNamer
Requires-Dist: fundamentals
Requires-Dist: requests
Requires-Dist: astrocalc
Requires-Dist: unicodecsv
Requires-Dist: numpy
Requires-Dist: python-dateutil
Requires-Dist: bs4
Requires-Dist: pandas
Requires-Dist: multiprocess
